[
  {
    "tt_beta": 0,
    "beta_set": 0.0862,
    "date": "2020-03-10",
    "Rt": 3.2,
    "Meff": 7.3,
    "grey_bar_start": false
  },
  {
    "tt_beta": 1,
    "beta_set": 0.1056,
    "date": "2020-03-11",
    "Rt": 3.9176,
    "Meff": 7.3,
    "grey_bar_start": false
  },
  {
    "tt_beta": 3,
    "beta_set": 0.1136,
    "date": "2020-03-13",
    "Rt": 4.215,
    "Meff": 7.3,
    "grey_bar_start": false
  },
  {
    "tt_beta": 4,
    "beta_set": 0.1129,
    "date": "2020-03-14",
    "Rt": 4.1886,
    "Meff": 7.3,
    "grey_bar_start": false
  },
  {
    "tt_beta": 5,
    "beta_set": 0.1018,
    "date": "2020-03-15",
    "Rt": 3.7776,
    "Meff": 7.3,
    "grey_bar_start": false
  },
  {
    "tt_beta": 6,
    "beta_set": 0.1143,
    "date": "2020-03-16",
    "Rt": 4.2411,
    "Meff": 7.3,
    "grey_bar_start": false
  },
  {
    "tt_beta": 7,
    "beta_set": 0.1086,
    "date": "2020-03-17",
    "Rt": 4.0276,
    "Meff": 7.3,
    "grey_bar_start": false
  },
  {
    "tt_beta": 8,
    "beta_set": 0.1078,
    "date": "2020-03-18",
    "Rt": 4.0003,
    "Meff": 7.3,
    "grey_bar_start": false
  },
  {
    "tt_beta": 9,
    "beta_set": 0.1026,
    "date": "2020-03-19",
    "Rt": 3.8058,
    "Meff": 7.3,
    "grey_bar_start": false
  },
  {
    "tt_beta": 10,
    "beta_set": 0.1003,
    "date": "2020-03-20",
    "Rt": 3.7209,
    "Meff": 7.3,
    "grey_bar_start": false
  },
  {
    "tt_beta": 11,
    "beta_set": 0.0365,
    "date": "2020-03-21",
    "Rt": 1.3556,
    "Meff": 7.3,
    "grey_bar_start": false
  },
  {
    "tt_beta": 12,
    "beta_set": 0.0554,
    "date": "2020-03-22",
    "Rt": 2.0557,
    "Meff": 7.3,
    "grey_bar_start": false
  },
  {
    "tt_beta": 13,
    "beta_set": 0.0255,
    "date": "2020-03-23",
    "Rt": 0.9459,
    "Meff": 7.3,
    "grey_bar_start": false
  },
  {
    "tt_beta": 14,
    "beta_set": 0.0267,
    "date": "2020-03-24",
    "Rt": 0.9909,
    "Meff": 7.3,
    "grey_bar_start": false
  },
  {
    "tt_beta": 15,
    "beta_set": 0.0311,
    "date": "2020-03-25",
    "Rt": 1.1535,
    "Meff": 7.3,
    "grey_bar_start": false
  },
  {
    "tt_beta": 16,
    "beta_set": 0.0481,
    "date": "2020-03-26",
    "Rt": 1.7862,
    "Meff": 7.3,
    "grey_bar_start": false
  },
  {
    "tt_beta": 17,
    "beta_set": 0.0692,
    "date": "2020-03-27",
    "Rt": 2.5661,
    "Meff": 7.3,
    "grey_bar_start": false
  },
  {
    "tt_beta": 18,
    "beta_set": 0.0722,
    "date": "2020-03-28",
    "Rt": 2.6791,
    "Meff": 7.3,
    "grey_bar_start": false
  },
  {
    "tt_beta": 19,
    "beta_set": 0.0684,
    "date": "2020-03-29",
    "Rt": 2.5381,
    "Meff": 7.3,
    "grey_bar_start": false
  },
  {
    "tt_beta": 20,
    "beta_set": 0.0722,
    "date": "2020-03-30",
    "Rt": 2.6791,
    "Meff": 7.3,
    "grey_bar_start": false
  },
  {
    "tt_beta": 21,
    "beta_set": 0.0625,
    "date": "2020-03-31",
    "Rt": 2.3182,
    "Meff": 7.3,
    "grey_bar_start": false
  },
  {
    "tt_beta": 22,
    "beta_set": 0.0568,
    "date": "2020-04-01",
    "Rt": 2.107,
    "Meff": 7.3,
    "grey_bar_start": false
  },
  {
    "tt_beta": 23,
    "beta_set": 0.0776,
    "date": "2020-04-02",
    "Rt": 2.8799,
    "Meff": 7.3,
    "grey_bar_start": false
  },
  {
    "tt_beta": 24,
    "beta_set": 0.087,
    "date": "2020-04-03",
    "Rt": 3.2292,
    "Meff": 7.3,
    "grey_bar_start": false
  },
  {
    "tt_beta": 25,
    "beta_set": 0.0823,
    "date": "2020-04-04",
    "Rt": 3.0541,
    "Meff": 7.3,
    "grey_bar_start": false
  },
  {
    "tt_beta": 26,
    "beta_set": 0.0699,
    "date": "2020-04-05",
    "Rt": 2.5942,
    "Meff": 7.3,
    "grey_bar_start": false
  },
  {
    "tt_beta": 27,
    "beta_set": 0.0776,
    "date": "2020-04-06",
    "Rt": 2.8799,
    "Meff": 7.3,
    "grey_bar_start": false
  },
  {
    "tt_beta": 28,
    "beta_set": 0.0714,
    "date": "2020-04-07",
    "Rt": 2.6507,
    "Meff": 7.3,
    "grey_bar_start": false
  },
  {
    "tt_beta": 29,
    "beta_set": 0.0589,
    "date": "2020-04-08",
    "Rt": 2.185,
    "Meff": 7.3,
    "grey_bar_start": false
  },
  {
    "tt_beta": 30,
    "beta_set": 0.0494,
    "date": "2020-04-09",
    "Rt": 1.8335,
    "Meff": 7.3,
    "grey_bar_start": false
  },
  {
    "tt_beta": 31,
    "beta_set": 0.0831,
    "date": "2020-04-10",
    "Rt": 3.0833,
    "Meff": 7.3,
    "grey_bar_start": false
  },
  {
    "tt_beta": 32,
    "beta_set": 0.073,
    "date": "2020-04-11",
    "Rt": 2.7075,
    "Meff": 7.3,
    "grey_bar_start": false
  },
  {
    "tt_beta": 33,
    "beta_set": 0.0507,
    "date": "2020-04-12",
    "Rt": 1.8816,
    "Meff": 7.3,
    "grey_bar_start": false
  },
  {
    "tt_beta": 34,
    "beta_set": 0.0632,
    "date": "2020-04-13",
    "Rt": 2.3452,
    "Meff": 7.3,
    "grey_bar_start": false
  },
  {
    "tt_beta": 35,
    "beta_set": 0.0647,
    "date": "2020-04-14",
    "Rt": 2.3997,
    "Meff": 7.3,
    "grey_bar_start": false
  },
  {
    "tt_beta": 36,
    "beta_set": 0.0561,
    "date": "2020-04-15",
    "Rt": 2.0812,
    "Meff": 7.3,
    "grey_bar_start": false
  },
  {
    "tt_beta": 37,
    "beta_set": 0.0792,
    "date": "2020-04-16",
    "Rt": 2.9378,
    "Meff": 7.3,
    "grey_bar_start": false
  },
  {
    "tt_beta": 38,
    "beta_set": 0.0823,
    "date": "2020-04-17",
    "Rt": 3.0541,
    "Meff": 7.3,
    "grey_bar_start": false
  },
  {
    "tt_beta": 39,
    "beta_set": 0.0707,
    "date": "2020-04-18",
    "Rt": 2.6224,
    "Meff": 7.3,
    "grey_bar_start": true
  },
  {
    "tt_beta": 40,
    "beta_set": 0.0554,
    "date": "2020-04-19",
    "Rt": 2.0557,
    "Meff": 7.3,
    "grey_bar_start": false
  },
  {
    "tt_beta": 41,
    "beta_set": 0.0654,
    "date": "2020-04-20",
    "Rt": 2.4272,
    "Meff": 7.3,
    "grey_bar_start": false
  },
  {
    "tt_beta": 42,
    "beta_set": 0.0618,
    "date": "2020-04-21",
    "Rt": 2.2913,
    "Meff": 7.3,
    "grey_bar_start": false
  },
  {
    "tt_beta": 43,
    "beta_set": 0.061,
    "date": "2020-04-22",
    "Rt": 2.2645,
    "Meff": 7.3,
    "grey_bar_start": false
  },
  {
    "tt_beta": 44,
    "beta_set": 0.0618,
    "date": "2020-04-23",
    "Rt": 2.2913,
    "Meff": 7.3,
    "grey_bar_start": false
  },
  {
    "tt_beta": 45,
    "beta_set": 0.0392,
    "date": "2020-04-24",
    "Rt": 1.4557,
    "Meff": 7.3,
    "grey_bar_start": false
  },
  {
    "tt_beta": 46,
    "beta_set": 0.0355,
    "date": "2020-04-25",
    "Rt": 1.317,
    "Meff": 7.3,
    "grey_bar_start": false
  },
  {
    "tt_beta": 47,
    "beta_set": 0.0288,
    "date": "2020-04-26",
    "Rt": 1.0697,
    "Meff": 7.3,
    "grey_bar_start": false
  },
  {
    "tt_beta": 48,
    "beta_set": 0.0259,
    "date": "2020-04-27",
    "Rt": 0.9607,
    "Meff": 7.3,
    "grey_bar_start": false
  },
  {
    "tt_beta": 49,
    "beta_set": 0.0232,
    "date": "2020-04-28",
    "Rt": 0.861,
    "Meff": 7.3,
    "grey_bar_start": false
  },
  {
    "tt_beta": 50,
    "beta_set": 0.0236,
    "date": "2020-04-29",
    "Rt": 0.8747,
    "Meff": 7.3,
    "grey_bar_start": false
  },
  {
    "tt_beta": 51,
    "beta_set": 0.0204,
    "date": "2020-04-30",
    "Rt": 0.7579,
    "Meff": 7.3,
    "grey_bar_start": false
  },
  {
    "tt_beta": 52,
    "beta_set": 0.014,
    "date": "2020-05-01",
    "Rt": 0.5192,
    "Meff": 7.3,
    "grey_bar_start": false
  },
  {
    "tt_beta": 53,
    "beta_set": 0.009,
    "date": "2020-05-02",
    "Rt": 0.3332,
    "Meff": 7.3,
    "grey_bar_start": false
  },
  {
    "tt_beta": 54,
    "beta_set": 0.008,
    "date": "2020-05-03",
    "Rt": 0.2951,
    "Meff": 7.3,
    "grey_bar_start": false
  },
  {
    "tt_beta": 55,
    "beta_set": 0.007,
    "date": "2020-05-04",
    "Rt": 0.2612,
    "Meff": 7.3,
    "grey_bar_start": false
  },
  {
    "tt_beta": 56,
    "beta_set": 0.0064,
    "date": "2020-05-05",
    "Rt": 0.2392,
    "Meff": 7.3,
    "grey_bar_start": false
  },
  {
    "tt_beta": 57,
    "beta_set": 0.0075,
    "date": "2020-05-06",
    "Rt": 0.2801,
    "Meff": 7.3,
    "grey_bar_start": false
  },
  {
    "tt_beta": 58,
    "beta_set": 0.0074,
    "date": "2020-05-07",
    "Rt": 0.2752,
    "Meff": 7.3,
    "grey_bar_start": false
  },
  {
    "tt_beta": 59,
    "beta_set": 0.0077,
    "date": "2020-05-08",
    "Rt": 0.285,
    "Meff": 7.3,
    "grey_bar_start": false
  },
  {
    "tt_beta": 60,
    "beta_set": 0.0062,
    "date": "2020-05-09",
    "Rt": 0.231,
    "Meff": 7.3,
    "grey_bar_start": false
  },
  {
    "tt_beta": 61,
    "beta_set": 0.0087,
    "date": "2020-05-10",
    "Rt": 0.3219,
    "Meff": 7.3,
    "grey_bar_start": false
  },
  {
    "tt_beta": 62,
    "beta_set": 0.0061,
    "date": "2020-05-11",
    "Rt": 0.2269,
    "Meff": 7.3,
    "grey_bar_start": false
  },
  {
    "tt_beta": 63,
    "beta_set": 0.0082,
    "date": "2020-05-12",
    "Rt": 0.3056,
    "Meff": 7.3,
    "grey_bar_start": false
  },
  {
    "tt_beta": 64,
    "beta_set": 0.0068,
    "date": "2020-05-13",
    "Rt": 0.2522,
    "Meff": 7.3,
    "grey_bar_start": false
  },
  {
    "tt_beta": 65,
    "beta_set": 0.0054,
    "date": "2020-05-14",
    "Rt": 0.2006,
    "Meff": 7.3,
    "grey_bar_start": false
  },
  {
    "tt_beta": 66,
    "beta_set": 0.009,
    "date": "2020-05-15",
    "Rt": 0.3332,
    "Meff": 7.3,
    "grey_bar_start": false
  },
  {
    "tt_beta": 67,
    "beta_set": 0.0078,
    "date": "2020-05-16",
    "Rt": 0.29,
    "Meff": 7.3,
    "grey_bar_start": false
  },
  {
    "tt_beta": 68,
    "beta_set": 0.011,
    "date": "2020-05-17",
    "Rt": 0.4096,
    "Meff": 7.3,
    "grey_bar_start": false
  },
  {
    "tt_beta": 69,
    "beta_set": 0.007,
    "date": "2020-05-18",
    "Rt": 0.2612,
    "Meff": 7.3,
    "grey_bar_start": false
  },
  {
    "tt_beta": 70,
    "beta_set": 0.0093,
    "date": "2020-05-19",
    "Rt": 0.3449,
    "Meff": 7.3,
    "grey_bar_start": false
  },
  {
    "tt_beta": 71,
    "beta_set": 0.0088,
    "date": "2020-05-20",
    "Rt": 0.3275,
    "Meff": 7.3,
    "grey_bar_start": false
  },
  {
    "tt_beta": 72,
    "beta_set": 0.0098,
    "date": "2020-05-21",
    "Rt": 0.3633,
    "Meff": 7.3,
    "grey_bar_start": false
  },
  {
    "tt_beta": 73,
    "beta_set": 0.0122,
    "date": "2020-05-22",
    "Rt": 0.4536,
    "Meff": 7.3,
    "grey_bar_start": false
  },
  {
    "tt_beta": 74,
    "beta_set": 0.0135,
    "date": "2020-05-23",
    "Rt": 0.502,
    "Meff": 7.3,
    "grey_bar_start": false
  },
  {
    "tt_beta": 75,
    "beta_set": 0.0066,
    "date": "2020-05-24",
    "Rt": 0.2435,
    "Meff": 7.3,
    "grey_bar_start": false
  },
  {
    "tt_beta": 76,
    "beta_set": 0.0051,
    "date": "2020-05-25",
    "Rt": 0.1902,
    "Meff": 7.3,
    "grey_bar_start": false
  },
  {
    "tt_beta": 77,
    "beta_set": 0.0103,
    "date": "2020-05-26",
    "Rt": 0.3825,
    "Meff": 7.3,
    "grey_bar_start": false
  },
  {
    "tt_beta": 78,
    "beta_set": 0.0109,
    "date": "2020-05-27",
    "Rt": 0.4027,
    "Meff": 7.3,
    "grey_bar_start": false
  },
  {
    "tt_beta": 79,
    "beta_set": 0.0114,
    "date": "2020-05-28",
    "Rt": 0.4238,
    "Meff": 7.3,
    "grey_bar_start": false
  },
  {
    "tt_beta": 80,
    "beta_set": 0.0131,
    "date": "2020-05-29",
    "Rt": 0.4854,
    "Meff": 7.3,
    "grey_bar_start": false
  },
  {
    "tt_beta": 81,
    "beta_set": 0.0096,
    "date": "2020-05-30",
    "Rt": 0.3579,
    "Meff": 7.3,
    "grey_bar_start": false
  }
]
